exosims_plugins/__init__.py
exosims_plugins/_version.py
exosims_plugins/Completeness/OrbixCompleteness.py
exosims_plugins/Completeness/__init__.py
exosims_plugins/SimulatedUniverse/OrbixUniverse.py
exosims_plugins/SimulatedUniverse/__init__.py
exosims_plugins/SurveySimulation/OrbixScheduler.py
exosims_plugins/SurveySimulation/__init__.py
exosims_plugins-1.0.2.dist-info/METADATA
exosims_plugins-1.0.2.dist-info/WHEEL
exosims_plugins-1.0.2.dist-info/licenses/LICENSE
exosims_plugins-1.0.2.dist-info/RECORD
