Metadata-Version: 2.4
Name: exosims-plugins
Version: 1.0.2
Summary: A library of plugins for EXOSIMS
Project-URL: Homepage, https://github.com/CoreySpohn/exosims-plugins
Project-URL: Issues, https://github.com/CoreySpohn/exosims-plugins/issues
License: MIT License
License-File: LICENSE
Requires-Python: >=3.10
Requires-Dist: exosims>=3.4.1
Requires-Dist: intervaltree>=3.1.0
Requires-Dist: orbix>=0.1.0
Provides-Extra: docs
Requires-Dist: matplotlib; extra == 'docs'
Requires-Dist: myst-nb; extra == 'docs'
Requires-Dist: sphinx; extra == 'docs'
Requires-Dist: sphinx-autoapi; extra == 'docs'
Requires-Dist: sphinx-autodoc-typehints; extra == 'docs'
Requires-Dist: sphinx-book-theme; extra == 'docs'
Provides-Extra: exosims
Requires-Dist: exosims>=3.4.1; extra == 'exosims'
